motionminer/__init__.py
motionminer/__main__.py
motionminer/analyzer.py
motionminer/cli.py
motionminer/config.py
motionminer/convert.py
motionminer/converter.py
motionminer/extractor.py
motionminer/main.py
motionminer/py.typed
motionminer-1.1.0.dist-info/licenses/LICENSE
motionminer-1.1.0.dist-info/METADATA
motionminer-1.1.0.dist-info/WHEEL
motionminer-1.1.0.dist-info/entry_points.txt
motionminer-1.1.0.dist-info/top_level.txt
motionminer-1.1.0.dist-info/RECORD
