Metadata-Version: 2.4
Name: motionminer
Version: 1.1.0
Summary: Extract videos from Google Motion Photos with ease!
Author-email: Matt LaPaglia <matt@mattlapaglia.com>
Maintainer-email: Matt LaPaglia <matt@mattlapaglia.com>
License:                                  Apache License
Project-URL: Homepage, https://github.com/mlapaglia/MotionMiner
Project-URL: Repository, https://github.com/mlapaglia/motionminer.git
Project-URL: Issues, https://github.com/mlapaglia/motionminer/issues
Project-URL: Documentation, https://github.com/mlapaglia/motionminer#readme
Keywords: motion,photo,video,extraction,google,photos,gif,mp4
Classifier: Development Status :: 5 - Production/Stable
Classifier: Intended Audience :: End Users/Desktop
Classifier: Intended Audience :: Developers
Classifier: Topic :: Multimedia :: Video :: Conversion
Classifier: Topic :: Multimedia :: Graphics :: Graphics Conversion
Classifier: Programming Language :: Python :: 3
Classifier: Programming Language :: Python :: 3.8
Classifier: Programming Language :: Python :: 3.9
Classifier: Programming Language :: Python :: 3.10
Classifier: Programming Language :: Python :: 3.11
Classifier: Programming Language :: Python :: 3.12
Classifier: Operating System :: OS Independent
Classifier: Environment :: Console
Requires-Python: >=3.8
License-File: LICENSE
Requires-Dist: ffmpeg-python>=0.2.0
Provides-Extra: dev
Requires-Dist: pytest>=7.0.0; extra == "dev"
Requires-Dist: pytest-cov>=4.0.0; extra == "dev"
Requires-Dist: pytest-mock>=3.10.0; extra == "dev"
Requires-Dist: black>=22.0.0; extra == "dev"
Requires-Dist: flake8>=4.0.0; extra == "dev"
Requires-Dist: mypy>=0.950; extra == "dev"
Provides-Extra: test
Requires-Dist: pytest>=7.0.0; extra == "test"
Requires-Dist: pytest-cov>=4.0.0; extra == "test"
Requires-Dist: pytest-mock>=3.10.0; extra == "test"
Dynamic: license-file
